{
  "packName": "Lit",
  "totalArticles": 11736,
  "topSellersCount": 1056,
  "topPct": 38,
  "midPct": 32,
  "lowPct": 30,
  "ranking": [
    {
      "name": "Vidaxl",
      "topSellerArticles": 241,
      "potentialPct": 98
    },
    {
      "name": "Vie Moderne",
      "topSellerArticles": 211,
      "potentialPct": 98
    },
    {
      "name": "Maison Vibe",
      "topSellerArticles": 186,
      "potentialPct": 98
    },
    {
      "name": "Vente Unique",
      "topSellerArticles": 154,
      "potentialPct": 99
    },
    {
      "name": "Kids Literie",
      "topSellerArticles": 143,
      "potentialPct": 99
    },
    {
      "name": "House Partners",
      "topSellerArticles": 121,
      "potentialPct": 99
    },
    {
      "name": "1001jouets",
      "topSellerArticles": 113,
      "potentialPct": 99
    },
    {
      "name": "Ecd",
      "topSellerArticles": 105,
      "potentialPct": 99
    },
    {
      "name": "",
      "topSellerArticles": 103,
      "potentialPct": 99
    },
    {
      "name": "Homifab",
      "topSellerArticles": 99,
      "potentialPct": 99
    },
    {
      "name": "Ml Design",
      "topSellerArticles": 97,
      "potentialPct": 99
    },
    {
      "name": "Premium Xl",
      "topSellerArticles": 96,
      "potentialPct": 99
    }
  ]
}