[
  {
    "slug": "aurlane",
    "name": "Aurlane",
    "articlesAnalysed": 2132,
    "qualityScore": 80
  },
  {
    "slug": "cdiscount",
    "name": "Cdiscount",
    "articlesAnalysed": 1097686,
    "qualityScore": 76
  },
  {
    "slug": "amazon",
    "name": "Amazon",
    "articlesAnalysed": 241868,
    "qualityScore": 74
  },
  {
    "slug": "carrefour",
    "name": "Carrefour",
    "articlesAnalysed": 612868,
    "qualityScore": 66
  },
  {
    "slug": "conforama",
    "name": "Conforama",
    "articlesAnalysed": 365929,
    "qualityScore": 63
  },
  {
    "slug": "auchan",
    "name": "Auchan",
    "articlesAnalysed": 50193,
    "qualityScore": 62
  },
  {
    "slug": "allobebe",
    "name": "Allobebe",
    "articlesAnalysed": 14189,
    "qualityScore": 61
  },
  {
    "slug": "vente-unique",
    "name": "Vente Unique",
    "articlesAnalysed": 674111,
    "qualityScore": 58
  },
  {
    "slug": "boulanger",
    "name": "Boulanger",
    "articlesAnalysed": 229757,
    "qualityScore": 55
  },
  {
    "slug": "fnac",
    "name": "Fnac",
    "articlesAnalysed": 490794,
    "qualityScore": 53
  },
  {
    "slug": "darty",
    "name": "Darty",
    "articlesAnalysed": 783757,
    "qualityScore": 52
  },
  {
    "slug": "autourdebebe",
    "name": "Autourdebebe",
    "articlesAnalysed": 18253,
    "qualityScore": 52
  }
]