[
  {
    "slug": "moonia",
    "name": "Moonia",
    "articlesAnalysed": 78790,
    "articlesMatched": 678,
    "priceIndex": 90
  },
  {
    "slug": "1001jouets",
    "name": "1001jouets",
    "articlesAnalysed": 78790,
    "articlesMatched": 421,
    "priceIndex": 92
  },
  {
    "slug": "actisom",
    "name": "Actisom",
    "articlesAnalysed": 78790,
    "articlesMatched": 534,
    "priceIndex": 93
  },
  {
    "slug": "petits meubles",
    "name": "Petits Meubles",
    "articlesAnalysed": 78790,
    "articlesMatched": 1000,
    "priceIndex": 94
  },
  {
    "slug": "concept usine",
    "name": "Concept Usine",
    "articlesAnalysed": 78790,
    "articlesMatched": 382,
    "priceIndex": 96
  },
  {
    "slug": "habitat & jardin",
    "name": "Habitat & Jardin",
    "articlesAnalysed": 78790,
    "articlesMatched": 304,
    "priceIndex": 96
  },
  {
    "slug": "sommeil de plomb",
    "name": "Sommeil De Plomb",
    "articlesAnalysed": 78790,
    "articlesMatched": 2658,
    "priceIndex": 98
  },
  {
    "slug": "dmora",
    "name": "Dmora",
    "articlesAnalysed": 78790,
    "articlesMatched": 1224,
    "priceIndex": 98
  },
  {
    "slug": "indream",
    "name": "Indream",
    "articlesAnalysed": 78790,
    "articlesMatched": 763,
    "priceIndex": 98
  },
  {
    "slug": "best mobilier",
    "name": "Best Mobilier",
    "articlesAnalysed": 78790,
    "articlesMatched": 1893,
    "priceIndex": 100
  },
  {
    "slug": "beliani",
    "name": "Beliani",
    "articlesAnalysed": 78790,
    "articlesMatched": 3290,
    "priceIndex": 100
  },
  {
    "slug": "masseno",
    "name": "Masseno",
    "articlesAnalysed": 78790,
    "articlesMatched": 3876,
    "priceIndex": 100
  },
  {
    "slug": "vidaxl",
    "name": "Vidaxl",
    "articlesAnalysed": 78790,
    "articlesMatched": 2004,
    "priceIndex": 100
  },
  {
    "slug": "meublorama",
    "name": "Meublorama",
    "articlesAnalysed": 78790,
    "articlesMatched": 1065,
    "priceIndex": 100
  },
  {
    "slug": "the white stone",
    "name": "The White Stone",
    "articlesAnalysed": 78790,
    "articlesMatched": 780,
    "priceIndex": 100
  },
  {
    "slug": "id market",
    "name": "Id Market",
    "articlesAnalysed": 78790,
    "articlesMatched": 340,
    "priceIndex": 100
  },
  {
    "slug": "ok living",
    "name": "Ok Living",
    "articlesAnalysed": 78790,
    "articlesMatched": 1168,
    "priceIndex": 100
  },
  {
    "slug": "aosom",
    "name": "Aosom",
    "articlesAnalysed": 78790,
    "articlesMatched": 410,
    "priceIndex": 100
  },
  {
    "slug": "le quai des affaires",
    "name": "Le Quai Des Affaires",
    "articlesAnalysed": 78790,
    "articlesMatched": 336,
    "priceIndex": 100
  },
  {
    "slug": "pegane",
    "name": "Pegane",
    "articlesAnalysed": 78790,
    "articlesMatched": 579,
    "priceIndex": 100
  },
  {
    "slug": "paris prix",
    "name": "Paris Prix",
    "articlesAnalysed": 78790,
    "articlesMatched": 539,
    "priceIndex": 100
  },
  {
    "slug": "abiks meubles",
    "name": "Abiks Meubles",
    "articlesAnalysed": 78790,
    "articlesMatched": 5768,
    "priceIndex": 101
  },
  {
    "slug": "senso pur",
    "name": "Senso Pur",
    "articlesAnalysed": 78790,
    "articlesMatched": 414,
    "priceIndex": 101
  },
  {
    "slug": "sweeek",
    "name": "Sweeek",
    "articlesAnalysed": 78790,
    "articlesMatched": 516,
    "priceIndex": 102
  },
  {
    "slug": "idimex",
    "name": "Idimex",
    "articlesAnalysed": 78790,
    "articlesMatched": 267,
    "priceIndex": 102
  },
  {
    "slug": "literie moins cher",
    "name": "Literie Moins Cher",
    "articlesAnalysed": 78790,
    "articlesMatched": 4862,
    "priceIndex": 104
  },
  {
    "slug": "okwish",
    "name": "Okwish",
    "articlesAnalysed": 78790,
    "articlesMatched": 1468,
    "priceIndex": 104
  },
  {
    "slug": "idliterie",
    "name": "Idliterie",
    "articlesAnalysed": 78790,
    "articlesMatched": 237,
    "priceIndex": 105
  },
  {
    "slug": "vente unique",
    "name": "Vente Unique",
    "articlesAnalysed": 78790,
    "articlesMatched": 2858,
    "priceIndex": 107
  },
  {
    "slug": "redom",
    "name": "Redom",
    "articlesAnalysed": 78790,
    "articlesMatched": 966,
    "priceIndex": 109
  }
]