{
  "packName": "Plafonnier",
  "totalArticles": 852,
  "topSellersCount": 456,
  "topPct": 72,
  "midPct": 23,
  "lowPct": 5,
  "ranking": [
    {
      "name": "Nedgis",
      "topSellerArticles": 184,
      "potentialPct": 78
    },
    {
      "name": "Lemaitredeslampes",
      "topSellerArticles": 122,
      "potentialPct": 86
    },
    {
      "name": "Lamptwist",
      "topSellerArticles": 100,
      "potentialPct": 88
    },
    {
      "name": "Madeindesign",
      "topSellerArticles": 50,
      "potentialPct": 94
    },
    {
      "name": "Connox",
      "topSellerArticles": 44,
      "potentialPct": 95
    },
    {
      "name": "Asteri",
      "topSellerArticles": 43,
      "potentialPct": 95
    },
    {
      "name": "Light11",
      "topSellerArticles": 27,
      "potentialPct": 97
    },
    {
      "name": "The Cool Republic",
      "topSellerArticles": 22,
      "potentialPct": 97
    },
    {
      "name": "Myareadesign",
      "topSellerArticles": 9,
      "potentialPct": 99
    },
    {
      "name": "Dbs Rdc",
      "topSellerArticles": 7,
      "potentialPct": 99
    },
    {
      "name": "Evolutiv Solutions",
      "topSellerArticles": 6,
      "potentialPct": 99
    },
    {
      "name": "Nordlux",
      "topSellerArticles": 4,
      "potentialPct": 100
    }
  ]
}