{
  "packName": "Ordinateur portable",
  "totalArticles": 3645,
  "topSellersCount": 1420,
  "topPct": 43,
  "midPct": 35,
  "lowPct": 22,
  "ranking": [
    {
      "brand": "Kiatoo",
      "count": 392,
      "potentialPct": 89
    },
    {
      "brand": "Gpasplus",
      "count": 243,
      "potentialPct": 93
    },
    {
      "brand": "Topbiz",
      "count": 223,
      "potentialPct": 94
    },
    {
      "brand": "Darty",
      "count": 197,
      "potentialPct": 95
    },
    {
      "brand": "Monsieurplus",
      "count": 195,
      "potentialPct": 95
    },
    {
      "brand": "Cdiscount",
      "count": 170,
      "potentialPct": 95
    },
    {
      "brand": "Icoza",
      "count": 156,
      "potentialPct": 96
    },
    {
      "brand": "Rue Du Commerce",
      "count": 153,
      "potentialPct": 96
    },
    {
      "brand": "Leasi",
      "count": 150,
      "potentialPct": 96
    },
    {
      "brand": "Okamac",
      "count": 138,
      "potentialPct": 96
    },
    {
      "brand": "House Partners",
      "count": 126,
      "potentialPct": 97
    },
    {
      "brand": "Fnac 2nde Vie",
      "count": 118,
      "potentialPct": 97
    }
  ]
}